finite_state_sdk/__init__.py
finite_state_sdk/queries.py
finite_state_sdk/token_cache.py
finite_state_sdk-0.1.17.dist-info/LICENSE
finite_state_sdk-0.1.17.dist-info/METADATA
finite_state_sdk-0.1.17.dist-info/WHEEL
finite_state_sdk-0.1.17.dist-info/RECORD
