Metadata-Version: 2.1
Name: finite-state-sdk
Version: 0.1.17
Summary: The official Finite State Python SDK.
Home-page: https://github.com/FiniteStateInc/finite-state-sdk-python
License: MIT
Author: Finite State, Inc.
Author-email: developer-tools@finitestate.io
Maintainer: Finite State, Inc.
Maintainer-email: developer-tools@finitestate.io
Requires-Python: >=3.11,<4.0
Classifier: Development Status :: 4 - Beta
Classifier: Intended Audience :: Developers
Classifier: License :: OSI Approved :: MIT License
Classifier: Natural Language :: English
Classifier: Operating System :: OS Independent
Classifier: Programming Language :: Python :: 3
Classifier: Programming Language :: Python :: 3.11
Classifier: Programming Language :: Python :: 3.10
Classifier: Programming Language :: Python :: 3.12
Classifier: Programming Language :: Python :: 3.9
Classifier: Topic :: Security
Classifier: Topic :: Software Development :: Libraries :: Python Modules
Requires-Dist: Jinja2 (>=3.1.2,<4.0.0)
Requires-Dist: MarkupSafe (>=2.1.3,<3.0.0)
Requires-Dist: Pygments (>=2.15.1,<3.0.0)
Requires-Dist: bleach (>=6.1.0,<7.0.0)
Requires-Dist: build (>=1.2.1,<2.0.0)
Requires-Dist: certifi (>=2024.2.2,<2025.0.0)
Requires-Dist: charset-normalizer (>=3.2.0,<4.0.0)
Requires-Dist: cyclonedx-bom (==3.11.7)
Requires-Dist: cyclonedx-python-lib (==3.1.5)
Requires-Dist: docutils (>=0.21.1,<0.22.0)
Requires-Dist: idna (>=3.4,<4.0)
Requires-Dist: importlib-metadata (>=7.1.0,<8.0.0)
Requires-Dist: jaraco-classes (>=3.3.0,<4.0.0)
Requires-Dist: keyring (>=25.1.0,<26.0.0)
Requires-Dist: markdown-it-py (>=3.0.0,<4.0.0)
Requires-Dist: mdurl (>=0.1.2,<0.2.0)
Requires-Dist: more-itertools (>=10.2.0,<11.0.0)
Requires-Dist: packageurl-python (>=0.15.0,<0.16.0)
Requires-Dist: packaging (>=24.0,<25.0)
Requires-Dist: pdoc (>=14.0.0,<15.0.0)
Requires-Dist: pip-requirements-parser (>=32.0.1,<33.0.0)
Requires-Dist: pkginfo (>=1.9.6,<2.0.0)
Requires-Dist: pyparsing (>=3.1.0,<4.0.0)
Requires-Dist: pyproject_hooks (>=1.0.0,<2.0.0)
Requires-Dist: readme-renderer (>=43.0,<44.0)
Requires-Dist: requests (>=2.31.0,<3.0.0)
Requires-Dist: requests-toolbelt (>=1.0.0,<2.0.0)
Requires-Dist: rfc3986 (>=2.0.0,<3.0.0)
Requires-Dist: six (>=1.16.0,<2.0.0)
Requires-Dist: sortedcontainers (>=2.4.0,<3.0.0)
Requires-Dist: toml (>=0.10.2,<0.11.0)
Requires-Dist: tomli (>=2.0.1,<3.0.0)
Requires-Dist: twine (>=5.0.0,<6.0.0)
Requires-Dist: urllib3 (>=2.0.3,<3.0.0)
Requires-Dist: webencodings (>=0.5.1,<0.6.0)
Requires-Dist: zipp (>=3.16.2,<4.0.0)
Project-URL: Repository, https://www.github.com/FiniteStateInc/finite-state-sdk-python
